loads/__init__.py
loads/datasource_io/__init__.py
loads/datasource_io/mongodbio.py
loads/loads_utils/__init__.py
loads/loads_utils/loads.py
loads_pipeline-0.3.dist-info/LICENSE
loads_pipeline-0.3.dist-info/METADATA
loads_pipeline-0.3.dist-info/WHEEL
loads_pipeline-0.3.dist-info/top_level.txt
loads_pipeline-0.3.dist-info/RECORD
